nextqsm/__init__.py
nextqsm/predict_all.py
nextqsm/checkpoints/checkpoint
nextqsm/checkpoints/params.json
nextqsm/models/__init__.py
nextqsm/models/solver_all.py
nextqsm/models/varnet.py
nextqsm/processing/__init__.py
nextqsm/processing/data_loader.py
nextqsm/processing/qsm.py
nextqsm/tests/__init__.py
nextqsm/tests/test_nextqsm.py
nextqsm/tf_utils/__init__.py
nextqsm/tf_utils/metrics.py
nextqsm/tf_utils/misc.py
nextqsm/tf_utils/blocks/__init__.py
nextqsm/tf_utils/blocks/cnn_block.py
nextqsm/tf_utils/nets/__init__.py
nextqsm/tf_utils/nets/unet.py
nextqsm-1.0.4.dist-info/LICENSE
nextqsm-1.0.4.dist-info/METADATA
nextqsm-1.0.4.dist-info/WHEEL
nextqsm-1.0.4.dist-info/entry_points.txt
nextqsm-1.0.4.dist-info/top_level.txt
nextqsm-1.0.4.dist-info/RECORD
