Metadata-Version: 2.1
Name: nextqsm
Version: 1.0.4
License-File: LICENSE
Requires-Dist: tensorflow
Requires-Dist: packaging
Requires-Dist: osfclient
